km3net_testdata/__init__.py
km3net_testdata/__main__.py
km3net_testdata/version.py
km3net_testdata/data/__init__.py
km3net_testdata/data/acoustics/DOM_808956920_CH1_1608751683.bin
km3net_testdata/data/astro/ARCA_astro_objects_benchmark.csv
km3net_testdata/data/astro/ARCA_coordinate_systems_benchmark.csv
km3net_testdata/data/astro/ARCA_moon_sun_position_benchmark.csv
km3net_testdata/data/astro/ORCA_astro_objects_benchmark.csv
km3net_testdata/data/astro/ORCA_coordinate_systems_benchmark.csv
km3net_testdata/data/astro/ORCA_moon_sun_position_benchmark.csv
km3net_testdata/data/astro/antares_astro_objects_benchmark.csv
km3net_testdata/data/astro/antares_coordinate_systems_benchmark.csv
km3net_testdata/data/astro/antares_moon_sun_position_benchmark.csv
km3net_testdata/data/astro/local2eq_aanet_2.7.0.csv
km3net_testdata/data/astro/local2eq_aanet_2.7.0.py
km3net_testdata/data/calib/KM3NeT_00000049_0.0.0_00007631_00007676_1.orientations.root
km3net_testdata/data/calib/KM3NeT_00000133_D_1.0.0_00017397_00017496_1.orientations.root
km3net_testdata/data/calib/PMTeff.txt
km3net_testdata/data/corsika/DAT000001
km3net_testdata/data/corsika/datacard_run_000001.inp
km3net_testdata/data/corsika/datacard_run_000001.out.gz
km3net_testdata/data/daq/IO_EVT.dat
km3net_testdata/data/daq/IO_EVT_legacy.dat
km3net_testdata/data/daq/IO_MONIT.dat
km3net_testdata/data/daq/IO_SUM.dat
km3net_testdata/data/daq/IO_SUM_legacy.dat
km3net_testdata/data/daq/IO_TSL0_legacy.dat
km3net_testdata/data/daq/IO_TSL1_1003.dat
km3net_testdata/data/daq/IO_TSL1_legacy.dat
km3net_testdata/data/daq/IO_TSL2_legacy.dat
km3net_testdata/data/daq/IO_TSSN.dat
km3net_testdata/data/daq/clb.dqd
km3net_testdata/data/daq/clb_acoustics.csk
km3net_testdata/data/datx/KM3NeT_00000133_20221025.datx
km3net_testdata/data/db/HVtuning_APIv1.0.0_HV-TUNING-GAIN-v1.json
km3net_testdata/data/db/HVtuning_APIv1.0.0_HV-TUNING-GAIN-v2.json
km3net_testdata/data/db/HVtuning_APIv1.0.0_HV-TUNING-GAIN-v3.json
km3net_testdata-0.4.27.dist-info/LICENSE
km3net_testdata-0.4.27.dist-info/METADATA
km3net_testdata-0.4.27.dist-info/WHEEL
km3net_testdata-0.4.27.dist-info/top_level.txt
km3net_testdata-0.4.27.dist-info/RECORD
