Metadata-Version: 2.1
Name: km3net-testdata
Version: 0.4.27
Summary: KM3NeT TestData
Home-page: https://git.km3net.de/km3py/km3net-testdata
Author: Tamas Gal
Author-email: tgal@km3net.de
License: UNKNOWN
Platform: any
Classifier: Intended Audience :: Developers
Classifier: Intended Audience :: Science/Research
Classifier: Programming Language :: Python
Requires-Python: >=2.7
Requires-Dist: setuptools-scm
Requires-Dist: importlib-resources; python_version < "3.8"
Requires-Dist: importlib-metadata; python_version < "3.8"
Provides-Extra: dev
Requires-Dist: black==22.3.0; extra == "dev"
Requires-Dist: matplotlib; extra == "dev"
Requires-Dist: memory-profiler; extra == "dev"
Requires-Dist: numpydoc; extra == "dev"
Requires-Dist: pillow; extra == "dev"
Requires-Dist: pytest; extra == "dev"
Requires-Dist: pytest-cov; extra == "dev"
Requires-Dist: pytest-flake8; extra == "dev"
Requires-Dist: pylint; extra == "dev"
Requires-Dist: pytest-watch; extra == "dev"
Requires-Dist: sphinx; extra == "dev"
Requires-Dist: sphinx-autoapi; extra == "dev"
Requires-Dist: sphinx-gallery>=0.1.12; extra == "dev"
Requires-Dist: sphinx-rtd-theme; extra == "dev"
Requires-Dist: sphinxcontrib-versioning; extra == "dev"
Requires-Dist: wheel; extra == "dev"
